supergreen/__init__.py
supergreen-0.0.1.dist-info/METADATA
supergreen-0.0.1.dist-info/WHEEL
supergreen-0.0.1.dist-info/RECORD
